geo_calcite/__init__.py
geo_calcite/client.py
geo_calcite/response_body.py
geo_calcite-0.2.1.dist-info/licenses/LICENSE
geo_calcite-0.2.1.dist-info/licenses/NOTICE
geo_calcite-0.2.1.dist-info/METADATA
geo_calcite-0.2.1.dist-info/WHEEL
geo_calcite-0.2.1.dist-info/top_level.txt
geo_calcite-0.2.1.dist-info/RECORD
