Metadata-Version: 2.4
Name: geo_calcite
Version: 0.2.1
Summary: Python client for Geo-Calcite data service
Home-page: https://code.deep-time.org/Aoicat/geo-calcite-python-client
Author: Zhejiang University
License: Apache License 2.0
Classifier: Programming Language :: Python :: 3
Classifier: Operating System :: OS Independent
Requires-Python: >=3.6
License-File: LICENSE
License-File: NOTICE
Requires-Dist: requests>=2.0.0
Requires-Dist: pandas>=1.0.0
Dynamic: author
Dynamic: classifier
Dynamic: description
Dynamic: description-content-type
Dynamic: home-page
Dynamic: license
Dynamic: license-file
Dynamic: requires-dist
Dynamic: requires-python
Dynamic: summary
